Metadata-Version: 2.1
Name: p8
Version: 0.1.3
Summary: The Python ultimate meta linter
Home-page: https://github.com/hvnsweeting/p8
Author: Viet Hung Nguyen
Author-email: hvn@familug.org
License: MIT
Platform: UNKNOWN
Classifier: Environment :: Console
